video_to_sqlite/__init__.py
video_to_sqlite/callback.py
video_to_sqlite/cli.py
video_to_sqlite-0.0.2.dist-info/LICENSE
video_to_sqlite-0.0.2.dist-info/METADATA
video_to_sqlite-0.0.2.dist-info/WHEEL
video_to_sqlite-0.0.2.dist-info/entry_points.txt
video_to_sqlite-0.0.2.dist-info/top_level.txt
video_to_sqlite-0.0.2.dist-info/RECORD
