Metadata-Version: 2.1
Name: video-to-sqlite
Version: 0.0.2
Summary: Load data about a video file into SQLite
Home-page: https://github.com/ryanfox/video-to-sqlite
Author: Ryan Fox
License: ACSL v1.4 (https://anticapitalist.software)
Project-URL: Issues, https://github.com/ryanfox/video-to-sqlite/issues
Requires-Python: >=3.7
License-File: LICENSE
Requires-Dist: click
Requires-Dist: sqlite-utils
Requires-Dist: imageio[ffmpeg]
